{
  "raceId": "202608031003",
  "fetchedAt": "2026-05-24T12:41:34.750Z",
  "places": [
    {
      "place": 1,
      "waku": 1,
      "horseNumber": 1,
      "horseId": "2023106894",
      "horseName": "ハヤブササキチャン",
      "final3fSec": 35.1,
      "cornerPassing": null,
      "marginToWinnerSec": 0
    },
    {
      "place": 2,
      "waku": 7,
      "horseNumber": 15,
      "horseId": "2023101576",
      "horseName": "リン",
      "final3fSec": 35.3,
      "cornerPassing": null,
      "marginToWinnerSec": 0.55
    },
    {
      "place": 3,
      "waku": 2,
      "horseNumber": 4,
      "horseId": "2023102357",
      "horseName": "ブランチアウト",
      "final3fSec": 35.8,
      "cornerPassing": null,
      "marginToWinnerSec": 0.06
    },
    {
      "place": 4,
      "waku": 6,
      "horseNumber": 11,
      "horseId": "2023103431",
      "horseName": "キボウホー",
      "final3fSec": 35.2,
      "cornerPassing": null,
      "marginToWinnerSec": 0.12
    },
    {
      "place": 5,
      "waku": 8,
      "horseNumber": 18,
      "horseId": "2023100096",
      "horseName": "ジュエルブリス",
      "final3fSec": 35.4,
      "cornerPassing": null,
      "marginToWinnerSec": 0.12
    },
    {
      "place": 6,
      "waku": 2,
      "horseNumber": 3,
      "horseId": "2023103795",
      "horseName": "タイムレスフレアー",
      "final3fSec": 34.7,
      "cornerPassing": null,
      "marginToWinnerSec": 0.12
    },
    {
      "place": 7,
      "waku": 8,
      "horseNumber": 16,
      "horseId": "2023104936",
      "horseName": "メイショウノヴァス",
      "final3fSec": 35,
      "cornerPassing": null,
      "marginToWinnerSec": 0.165
    },
    {
      "place": 8,
      "waku": 3,
      "horseNumber": 5,
      "horseId": "2023103605",
      "horseName": "ルージュソムニウム",
      "final3fSec": 35.8,
      "cornerPassing": null,
      "marginToWinnerSec": 1
    },
    {
      "place": 9,
      "waku": 3,
      "horseNumber": 6,
      "horseId": "2023105537",
      "horseName": "エイシンリーガル",
      "final3fSec": 35,
      "cornerPassing": null,
      "marginToWinnerSec": 0.12
    },
    {
      "place": 10,
      "waku": 7,
      "horseNumber": 14,
      "horseId": "2023105646",
      "horseName": "パラフローラ",
      "final3fSec": 35.7,
      "cornerPassing": null,
      "marginToWinnerSec": 0.275
    },
    {
      "place": 11,
      "waku": 4,
      "horseNumber": 8,
      "horseId": "2023100490",
      "horseName": "ピンクパンサー",
      "final3fSec": 35.7,
      "cornerPassing": null,
      "marginToWinnerSec": 0.11
    },
    {
      "place": 12,
      "waku": 5,
      "horseNumber": 9,
      "horseId": "2023102101",
      "horseName": "フィエスタ",
      "final3fSec": 35.8,
      "cornerPassing": null,
      "marginToWinnerSec": 0.12
    },
    {
      "place": 13,
      "waku": 4,
      "horseNumber": 7,
      "horseId": "2023106084",
      "horseName": "ゴッドレイ",
      "final3fSec": 36.2,
      "cornerPassing": null,
      "marginToWinnerSec": 0.165
    },
    {
      "place": 14,
      "waku": 8,
      "horseNumber": 17,
      "horseId": "2023101700",
      "horseName": "ユウトザイシン",
      "final3fSec": 35.4,
      "cornerPassing": null,
      "marginToWinnerSec": 0.385
    },
    {
      "place": 15,
      "waku": 5,
      "horseNumber": 10,
      "horseId": "2023100785",
      "horseName": "アズライトアスール",
      "final3fSec": 35.5,
      "cornerPassing": null,
      "marginToWinnerSec": null
    },
    {
      "place": 16,
      "waku": 1,
      "horseNumber": 2,
      "horseId": "2023105237",
      "horseName": "アスクウルトラモア",
      "final3fSec": 36.3,
      "cornerPassing": null,
      "marginToWinnerSec": 0.385
    },
    {
      "place": 17,
      "waku": 7,
      "horseNumber": 13,
      "horseId": "2023105742",
      "horseName": "モズガネシア",
      "final3fSec": 37.6,
      "cornerPassing": null,
      "marginToWinnerSec": 3
    },
    {
      "place": 18,
      "waku": 6,
      "horseNumber": 12,
      "horseId": "2023101969",
      "horseName": "ミキノヒストリー",
      "final3fSec": 43.3,
      "cornerPassing": null,
      "marginToWinnerSec": null
    }
  ],
  "payouts": {
    "WIN": [
      {
        "numbers": [
          1
        ],
        "dividend": 210
      }
    ],
    "SHOW": [
      {
        "numbers": [
          1
        ],
        "dividend": 110
      },
      {
        "numbers": [
          15
        ],
        "dividend": 220
      },
      {
        "numbers": [
          4
        ],
        "dividend": 170
      }
    ],
    "REN": [
      {
        "numbers": [
          1,
          15
        ],
        "dividend": 1120
      }
    ],
    "WREN": [
      {
        "numbers": [
          1,
          15
        ],
        "dividend": 450
      },
      {
        "numbers": [
          1,
          4
        ],
        "dividend": 320
      },
      {
        "numbers": [
          4,
          15
        ],
        "dividend": 1090
      }
    ],
    "TRI": [
      {
        "numbers": [
          1,
          4,
          15
        ],
        "dividend": 2080
      }
    ]
  }
}
