{
  "raceId": "202605020704",
  "fetchedAt": "2026-05-16T11:45:31.665Z",
  "places": [
    {
      "place": 1,
      "horseId": "2023104576",
      "horseName": "カンティーナ",
      "time": "2:00.3",
      "margin": 0
    },
    {
      "place": 2,
      "horseId": "2023107004",
      "horseName": "ヒシナスキロ",
      "time": "2:00.3",
      "margin": 0.12
    },
    {
      "place": 3,
      "horseId": "2023102362",
      "horseName": "ブライトエアリー",
      "time": "2:00.4",
      "margin": 0.06
    },
    {
      "place": 4,
      "horseId": "2023105003",
      "horseName": "アールグレイ",
      "time": "2:00.4",
      "margin": 0.06
    },
    {
      "place": 5,
      "horseId": "2023106285",
      "horseName": "ボーントゥラブユー",
      "time": "2:00.5",
      "margin": 0.165
    },
    {
      "place": 6,
      "horseId": "2023103688",
      "horseName": "コンフィグシス",
      "time": "2:00.6",
      "margin": 0.11
    },
    {
      "place": 7,
      "horseId": "2023106183",
      "horseName": "シェリーシュシュ",
      "time": "2:00.6",
      "margin": null
    },
    {
      "place": 8,
      "horseId": "2023106482",
      "horseName": "コスモペンタス",
      "time": "2:00.6",
      "margin": 0.12
    },
    {
      "place": 9,
      "horseId": "2023105230",
      "horseName": "アニゴザントス",
      "time": "2:00.8",
      "margin": 0.165
    },
    {
      "place": 10,
      "horseId": "2023103514",
      "horseName": "ファンシーシェイプ",
      "time": "2:01.1",
      "margin": 0.385
    },
    {
      "place": 11,
      "horseId": "2023105408",
      "horseName": "ソアサージュ",
      "time": "2:01.2",
      "margin": 0.165
    },
    {
      "place": 12,
      "horseId": "2023105102",
      "horseName": "ダイユウヴェンティ",
      "time": "2:01.2",
      "margin": 0.12
    },
    {
      "place": 13,
      "horseId": "2023105760",
      "horseName": "クインズロベリア",
      "time": "2:01.2",
      "margin": 0.06
    }
  ]
}
